wterm/__init__.py
wterm/console.py
wterm/logging.py
wterm-0.0.7.dist-info/LICENSE.txt
wterm-0.0.7.dist-info/METADATA
wterm-0.0.7.dist-info/WHEEL
wterm-0.0.7.dist-info/top_level.txt
wterm-0.0.7.dist-info/RECORD
